{
  "base": "stations",
  "clouds": {
    "all": 75
  },
  "cod": 200,
  "coord": {
    "lat": -33.8922,
    "lon": 151.19
  },
  "dateName": "12:31:45 Friday 29 April",
  "dt": 1651199016,
  "id": 2171589,
  "isUploaded": true,
  "main": {
    "feels_like": 25.13,
    "grnd_level": null,
    "humidity": 73,
    "pressure": 1016,
    "sea_level": null,
    "temp": 24.7,
    "temp_max": 27.62,
    "temp_min": 22.24
  },
  "name": "Chippendale",
  "sys": {
    "country": "AU",
    "id": 2002865,
    "sunrise": 1651177671,
    "sunset": 1651216634,
    "type": 2
  },
  "timeStamp": "2022-04-29-12-31-45-025",
  "timezone": 36000,
  "visibility": 10000,
  "weather": [
    {
      "description": "broken clouds",
      "icon": "04d",
      "id": 803,
      "main": "Clouds"
    }
  ],
  "wind": {
    "deg": 230,
    "gust": null,
    "speed": 3.09
  }
}